deferred/admin.py
deferred/models.py
deferred/helpers.py
deferred/__init__.py
deferred/management/__init__.py
deferred/management/commands/process_deferred.py
deferred/management/commands/__init__.py
django_triflesoft_deferred-0.1.1509191803.dist-info/RECORD
django_triflesoft_deferred-0.1.1509191803.dist-info/WHEEL
django_triflesoft_deferred-0.1.1509191803.dist-info/DESCRIPTION.rst
django_triflesoft_deferred-0.1.1509191803.dist-info/top_level.txt
django_triflesoft_deferred-0.1.1509191803.dist-info/METADATA
django_triflesoft_deferred-0.1.1509191803.dist-info/metadata.json
